deduplicationdict/__init__.py
deduplicationdict/py.typed
deduplicationdict-1.0.4.dist-info/LICENSE
deduplicationdict-1.0.4.dist-info/WHEEL
deduplicationdict-1.0.4.dist-info/METADATA
deduplicationdict-1.0.4.dist-info/RECORD
